chunkhound/__init__.py
chunkhound/chunker.py
chunkhound/database.py
chunkhound/database_factory.py
chunkhound/embeddings.py
chunkhound/file_discovery_cache.py
chunkhound/parser.py
chunkhound/py.typed
chunkhound/tree_cache.py
chunkhound/version.py
chunkhound/api/__init__.py
chunkhound/api/cli/CLAUDE.md
chunkhound/api/cli/__init__.py
chunkhound/api/cli/ascii_art.py
chunkhound/api/cli/env_detector.py
chunkhound/api/cli/keyboard.py
chunkhound/api/cli/main.py
chunkhound/api/cli/setup_wizard.py
chunkhound/api/cli/commands/__init__.py
chunkhound/api/cli/commands/mcp.py
chunkhound/api/cli/commands/run.py
chunkhound/api/cli/commands/search.py
chunkhound/api/cli/parsers/__init__.py
chunkhound/api/cli/parsers/common_arguments.py
chunkhound/api/cli/parsers/main_parser.py
chunkhound/api/cli/parsers/mcp_parser.py
chunkhound/api/cli/parsers/run_parser.py
chunkhound/api/cli/parsers/search_parser.py
chunkhound/api/cli/terminal/__init__.py
chunkhound/api/cli/terminal/core.py
chunkhound/api/cli/terminal/exceptions.py
chunkhound/api/cli/terminal/filters.py
chunkhound/api/cli/terminal/providers/__init__.py
chunkhound/api/cli/terminal/providers/base.py
chunkhound/api/cli/terminal/providers/unix.py
chunkhound/api/cli/terminal/providers/windows.py
chunkhound/api/cli/utils/__init__.py
chunkhound/api/cli/utils/config_factory.py
chunkhound/api/cli/utils/rich_output.py
chunkhound/api/cli/utils/text_input.py
chunkhound/api/cli/utils/validation.py
chunkhound/core/CLAUDE.md
chunkhound/core/__init__.py
chunkhound/core/constants.py
chunkhound/core/config/__init__.py
chunkhound/core/config/config.py
chunkhound/core/config/database_config.py
chunkhound/core/config/embedding_config.py
chunkhound/core/config/embedding_factory.py
chunkhound/core/config/indexing_config.py
chunkhound/core/config/mcp_config.py
chunkhound/core/config/openai_utils.py
chunkhound/core/config/settings_sources.py
chunkhound/core/exceptions/__init__.py
chunkhound/core/exceptions/core.py
chunkhound/core/models/__init__.py
mseep_chunkhound-3.2.2.dist-info/METADATA
mseep_chunkhound-3.2.2.dist-info/WHEEL
mseep_chunkhound-3.2.2.dist-info/entry_points.txt
mseep_chunkhound-3.2.2.dist-info/licenses/LICENSE
mseep_chunkhound-3.2.2.dist-info/RECORD
