Metadata-Version: 2.4
Name: mseep-chunkhound
Version: 3.2.2
Summary: Local-first semantic code search with vector and regex capabilities for AI assistants via MCP
Project-URL: Homepage, https://github.com/chunkhound/chunkhound
Project-URL: Repository, https://github.com/chunkhound/chunkhound
Project-URL: Issues, https://github.com/chunkhound/chunkhound/issues
Project-URL: Documentation, https://github.com/chunkhound/chunkhound#readme
Project-URL: Changelog, https://github.com/chunkhound/chunkhound/releases
Author-email: mseep <support@skydeck.ai>
License-File: LICENSE
Classifier: Development Status :: 3 - Alpha
Classifier: Environment :: Console
Classifier: Intended Audience :: Developers
Classifier: License :: OSI Approved :: MIT License
Classifier: Operating System :: OS Independent
Classifier: Programming Language :: Python :: 3
Classifier: Programming Language :: Python :: 3.10
Classifier: Programming Language :: Python :: 3.11
Classifier: Programming Language :: Python :: 3.12
Classifier: Programming Language :: Python :: 3.13
Classifier: Topic :: Internet :: WWW/HTTP :: Indexing/Search
Classifier: Topic :: Scientific/Engineering :: Artificial Intelligence
Classifier: Topic :: Software Development :: Code Generators
Classifier: Topic :: Software Development :: Libraries :: Python Modules
Classifier: Topic :: Text Processing :: Indexing
Requires-Python: >=3.10
Requires-Dist: aiohttp>=3.8.0
Requires-Dist: duckdb>=1.3.2
Requires-Dist: fastmcp>=2.0.0
Requires-Dist: httpx>=0.28.1
Requires-Dist: lancedb>=0.24.0
Requires-Dist: loguru>=0.6.0
Requires-Dist: mcp>=1.0.0
Requires-Dist: openai>=1.0.0
Requires-Dist: pandas>=2.3.0
Requires-Dist: psutil>=5.8.0
Requires-Dist: pydantic-settings>=2.0.0
Requires-Dist: pydantic>=2.0.0
Requires-Dist: pylance>=0.31.0
Requires-Dist: pymupdf>=1.23.0
Requires-Dist: pyyaml>=6.0.0
Requires-Dist: readchar>=4.2.1
Requires-Dist: rich>=13.0.0
Requires-Dist: tiktoken>=0.9.0
Requires-Dist: tree-sitter-bash<0.25.0,>=0.21.0
Requires-Dist: tree-sitter-c<0.23.0,>=0.21.0
Requires-Dist: tree-sitter-cpp<0.24.0,>=0.21.0
Requires-Dist: tree-sitter-go>=0.21.0
Requires-Dist: tree-sitter-groovy>=0.1.2
Requires-Dist: tree-sitter-java>=0.21.0
Requires-Dist: tree-sitter-javascript>=0.21.0
Requires-Dist: tree-sitter-json>=0.21.0
Requires-Dist: tree-sitter-kotlin>=0.3.0
Requires-Dist: tree-sitter-language-pack>=0.7.3
Requires-Dist: tree-sitter-make>=0.1.0
Requires-Dist: tree-sitter-markdown
Requires-Dist: tree-sitter-python>=0.20.0
Requires-Dist: tree-sitter-rust<0.23.0,>=0.21.0
Requires-Dist: tree-sitter-toml>=0.5.0
Requires-Dist: tree-sitter-typescript>=0.21.0
Requires-Dist: tree-sitter<0.24.0,>=0.23.0
Requires-Dist: voyageai>=0.2.0
Requires-Dist: watchdog>=4.0.0
Provides-Extra: dev
Requires-Dist: black>=23.0.0; extra == 'dev'
Requires-Dist: mypy>=1.6.0; extra == 'dev'
Requires-Dist: pytest-asyncio>=0.21.0; extra == 'dev'
Requires-Dist: pytest-timeout>=2.1.0; extra == 'dev'
Requires-Dist: pytest>=7.4.0; extra == 'dev'
Requires-Dist: ruff>=0.1.0; extra == 'dev'
Provides-Extra: test
Requires-Dist: pytest-asyncio>=0.21.0; extra == 'test'
Requires-Dist: pytest-timeout>=2.1.0; extra == 'test'
Requires-Dist: pytest>=7.4.0; extra == 'test'
